{"he":"ערערה בנגב","en":"Ar'ara BaNegev","semel":1192,"data":{"15":{"eligible":1646,"right_haredi_pct":3.58,"center_left_arab_pct":92.16,"right_pct":2.19,"haredi_pct":1.4,"center_pct":3.83,"left_pct":7.23,"arab_pct":81.11,"kosher_votes":1646,"bzb":2676,"voters":1729,"disqualified":83,"turnout_pct":64.6},"16":{"eligible":1489,"right_haredi_pct":3.76,"center_left_arab_pct":94.22,"right_pct":2.48,"haredi_pct":1.28,"center_pct":0.0,"left_pct":7.25,"arab_pct":86.97,"kosher_votes":1489,"bzb":3341,"voters":1544,"disqualified":55,"turnout_pct":46.2},"18":{"eligible":2664,"right_haredi_pct":1.31,"center_left_arab_pct":97.71,"right_pct":1.01,"haredi_pct":0.3,"center_pct":1.39,"left_pct":0.41,"arab_pct":95.91,"kosher_votes":2664,"bzb":4619,"voters":2709,"disqualified":45,"turnout_pct":58.6},"19":{"eligible":3784,"right_haredi_pct":1.24,"center_left_arab_pct":98.18,"right_pct":0.79,"haredi_pct":0.45,"center_pct":0.29,"left_pct":0.53,"arab_pct":97.36,"kosher_votes":3784,"bzb":5796,"voters":3798,"disqualified":14,"turnout_pct":65.5},"20":{"eligible":3701,"right_haredi_pct":2.27,"center_left_arab_pct":95.92,"right_pct":1.62,"haredi_pct":0.65,"center_pct":1.13,"left_pct":4.67,"arab_pct":90.11,"kosher_votes":3701,"bzb":6558,"voters":3773,"disqualified":72,"turnout_pct":57.5},"21":{"eligible":4593,"right_haredi_pct":3.2,"center_left_arab_pct":96.12,"right_pct":1.57,"haredi_pct":1.63,"center_pct":1.72,"left_pct":1.63,"arab_pct":92.77,"opposition_right_pct":0,"kosher_votes":4593,"bzb":8197,"voters":4635,"disqualified":42,"turnout_pct":56.5},"22":{"eligible":4356,"right_haredi_pct":2.3,"center_left_arab_pct":95.96,"right_pct":1.86,"haredi_pct":0.44,"center_pct":2.98,"left_pct":1.72,"arab_pct":91.25,"opposition_right_pct":0,"kosher_votes":4356,"bzb":8377,"voters":4387,"disqualified":31,"turnout_pct":52.4},"23":{"eligible":5087,"right_haredi_pct":0.47,"center_left_arab_pct":98.78,"right_pct":0.33,"haredi_pct":0.14,"center_pct":0.55,"left_pct":2.46,"arab_pct":95.75,"kosher_votes":5087,"opposition_right_pct":0.02,"bzb":8586,"voters":5113,"disqualified":26,"turnout_pct":59.6},"24":{"eligible":4353,"right_haredi_pct":1.72,"center_left_arab_pct":97.68,"right_pct":1.59,"haredi_pct":0.14,"center_pct":0.44,"left_pct":0.87,"arab_pct":96.21,"kosher_votes":4353,"opposition_right_pct":0.16,"bzb":9100,"voters":4378,"disqualified":25,"turnout_pct":48.1},"25":{"eligible":5567,"right_haredi_pct":0.81,"center_left_arab_pct":98.6,"right_pct":0.7,"haredi_pct":0.11,"center_pct":0.18,"left_pct":0.63,"arab_pct":97.79,"kosher_votes":5567,"opposition_right_pct":0.0,"bzb":9791,"voters":5599,"disqualified":32,"turnout_pct":57.2}}}