{"he":"שדה יעקב","en":"Sede Ya'aqov","semel":142,"data":{"14":{"eligible":266,"right_haredi_pct":69.17,"center_left_arab_pct":29.7,"right_pct":68.05,"haredi_pct":1.13,"center_pct":4.51,"left_pct":25.19,"arab_pct":0.0,"kosher_votes":266,"bzb":367,"voters":272,"disqualified":6,"turnout_pct":74.1},"15":{"eligible":240,"right_haredi_pct":67.92,"center_left_arab_pct":29.58,"right_pct":62.5,"haredi_pct":5.42,"center_pct":7.5,"left_pct":22.08,"arab_pct":0.0,"kosher_votes":240,"bzb":286,"voters":242,"disqualified":2,"turnout_pct":84.6},"16":{"eligible":238,"right_haredi_pct":79.83,"center_left_arab_pct":15.97,"right_pct":76.05,"haredi_pct":3.78,"center_pct":1.68,"left_pct":14.29,"arab_pct":0.0,"kosher_votes":238,"bzb":298,"voters":238,"disqualified":0,"turnout_pct":79.9},"17":{"eligible":284,"right_haredi_pct":69.01,"center_left_arab_pct":21.48,"right_pct":67.25,"haredi_pct":1.76,"center_pct":12.32,"left_pct":9.15,"arab_pct":0.0,"kosher_votes":284,"voters":285,"disqualified":1},"18":{"eligible":330,"right_haredi_pct":80.91,"center_left_arab_pct":18.18,"right_pct":77.88,"haredi_pct":3.03,"center_pct":9.39,"left_pct":8.79,"arab_pct":0.0,"kosher_votes":330,"bzb":402,"voters":330,"disqualified":0,"turnout_pct":82.1},"19":{"eligible":446,"right_haredi_pct":79.6,"center_left_arab_pct":17.94,"right_pct":78.25,"haredi_pct":1.35,"center_pct":6.95,"left_pct":10.99,"arab_pct":0.0,"kosher_votes":446,"bzb":523,"voters":447,"disqualified":1,"turnout_pct":85.5},"20":{"eligible":473,"right_haredi_pct":75.05,"center_left_arab_pct":24.31,"right_pct":69.98,"haredi_pct":5.07,"center_pct":14.59,"left_pct":9.73,"arab_pct":0.0,"kosher_votes":473,"bzb":562,"voters":473,"disqualified":0,"turnout_pct":84.2},"21":{"eligible":504,"right_haredi_pct":79.37,"center_left_arab_pct":20.04,"right_pct":77.98,"haredi_pct":1.39,"center_pct":14.68,"left_pct":4.96,"arab_pct":0.2,"opposition_right_pct":0.2,"kosher_votes":504,"bzb":614,"voters":504,"disqualified":0,"turnout_pct":82.1},"22":{"eligible":494,"right_haredi_pct":77.33,"center_left_arab_pct":20.65,"right_pct":74.09,"haredi_pct":3.24,"center_pct":13.16,"left_pct":6.28,"arab_pct":0.0,"opposition_right_pct":1.21,"bzb":626,"voters":494,"kosher_votes":494,"disqualified":0,"turnout_pct":78.9},"23":{"eligible":501,"right_haredi_pct":77.05,"center_left_arab_pct":22.95,"right_pct":74.25,"haredi_pct":2.79,"center_pct":18.36,"left_pct":3.59,"arab_pct":0.0,"kosher_votes":501,"opposition_right_pct":1.0,"bzb":628,"voters":502,"disqualified":1,"turnout_pct":79.9},"24":{"eligible":506,"right_haredi_pct":43.28,"center_left_arab_pct":54.94,"right_pct":41.7,"haredi_pct":1.58,"center_pct":10.08,"left_pct":5.53,"arab_pct":0.0,"kosher_votes":506,"opposition_right_pct":39.33,"bzb":651,"voters":507,"disqualified":1,"turnout_pct":77.9},"25":{"eligible":522,"right_haredi_pct":73.18,"center_left_arab_pct":25.67,"right_pct":71.46,"haredi_pct":1.72,"center_pct":21.65,"left_pct":3.26,"arab_pct":0.19,"kosher_votes":522,"opposition_right_pct":0.57,"bzb":671,"voters":524,"disqualified":2,"turnout_pct":78.1},"13":{"eligible":283,"right_haredi_pct":67.49,"center_left_arab_pct":30.04,"right_pct":61.48,"haredi_pct":6.01,"center_pct":0.0,"left_pct":29.68,"arab_pct":0.35,"kosher_votes":283,"bzb":390,"voters":285,"disqualified":2,"turnout_pct":73.1}}}