{"he":"חפץ חיים","en":"Hafez Hayyim","semel":363,"data":{"14":{"eligible":211,"right_haredi_pct":94.79,"center_left_arab_pct":3.79,"right_pct":78.67,"haredi_pct":16.11,"center_pct":0.95,"left_pct":2.84,"arab_pct":0.0,"kosher_votes":211,"bzb":255,"voters":215,"disqualified":4,"turnout_pct":84.3},"15":{"eligible":200,"right_haredi_pct":92.0,"center_left_arab_pct":5.5,"right_pct":41.0,"haredi_pct":51.0,"center_pct":0.5,"left_pct":4.5,"arab_pct":0.5,"kosher_votes":200,"bzb":240,"voters":201,"disqualified":1,"turnout_pct":83.8},"16":{"eligible":200,"right_haredi_pct":94.0,"center_left_arab_pct":1.5,"right_pct":74.5,"haredi_pct":19.5,"center_pct":0.5,"left_pct":1.0,"arab_pct":0.0,"kosher_votes":200,"bzb":242,"voters":200,"disqualified":0,"turnout_pct":82.6},"17":{"eligible":211,"right_haredi_pct":90.05,"center_left_arab_pct":2.37,"right_pct":64.45,"haredi_pct":25.59,"center_pct":1.9,"left_pct":0.47,"arab_pct":0.0,"kosher_votes":211,"voters":212,"disqualified":1},"18":{"eligible":240,"right_haredi_pct":95.42,"center_left_arab_pct":3.75,"right_pct":85.83,"haredi_pct":9.58,"center_pct":2.5,"left_pct":1.25,"arab_pct":0.0,"kosher_votes":240,"bzb":287,"voters":240,"disqualified":0,"turnout_pct":83.6},"19":{"eligible":314,"right_haredi_pct":94.59,"center_left_arab_pct":2.87,"right_pct":86.94,"haredi_pct":7.64,"center_pct":1.59,"left_pct":1.27,"arab_pct":0.0,"kosher_votes":314,"bzb":372,"voters":314,"disqualified":0,"turnout_pct":84.4},"20":{"eligible":281,"right_haredi_pct":95.37,"center_left_arab_pct":3.91,"right_pct":79.0,"haredi_pct":16.37,"center_pct":3.2,"left_pct":0.71,"arab_pct":0.0,"kosher_votes":281,"bzb":321,"voters":282,"disqualified":1,"turnout_pct":87.9},"21":{"eligible":301,"right_haredi_pct":97.01,"center_left_arab_pct":2.99,"right_pct":95.35,"haredi_pct":1.66,"center_pct":2.99,"left_pct":0.0,"arab_pct":0.0,"opposition_right_pct":0.0,"kosher_votes":301,"bzb":342,"voters":301,"disqualified":0,"turnout_pct":88.0},"22":{"eligible":284,"right_haredi_pct":95.77,"center_left_arab_pct":4.23,"right_pct":93.31,"haredi_pct":2.46,"center_pct":2.11,"left_pct":1.06,"arab_pct":0.0,"opposition_right_pct":1.06,"bzb":335,"voters":284,"kosher_votes":284,"disqualified":0,"turnout_pct":84.8},"23":{"eligible":286,"right_haredi_pct":96.5,"center_left_arab_pct":3.5,"right_pct":89.51,"haredi_pct":6.99,"center_pct":2.1,"left_pct":0.35,"arab_pct":0.0,"kosher_votes":286,"opposition_right_pct":1.05,"bzb":335,"voters":286,"disqualified":0,"turnout_pct":85.4},"24":{"eligible":289,"right_haredi_pct":67.82,"center_left_arab_pct":31.83,"right_pct":63.67,"haredi_pct":4.15,"center_pct":1.38,"left_pct":0.35,"arab_pct":0.0,"kosher_votes":289,"opposition_right_pct":30.1,"bzb":345,"voters":290,"disqualified":1,"turnout_pct":84.1},"25":{"eligible":307,"right_haredi_pct":95.77,"center_left_arab_pct":4.23,"right_pct":89.9,"haredi_pct":5.86,"center_pct":3.26,"left_pct":0.0,"arab_pct":0.0,"kosher_votes":307,"opposition_right_pct":0.98,"bzb":370,"voters":308,"disqualified":1,"turnout_pct":83.2},"13":{"eligible":187,"right_haredi_pct":97.33,"center_left_arab_pct":2.14,"right_pct":46.52,"haredi_pct":50.8,"center_pct":0.0,"left_pct":2.14,"arab_pct":0.0,"kosher_votes":187,"bzb":472,"voters":188,"disqualified":1,"turnout_pct":39.8}}}