{"he":"גלאון","en":"Gal'on","semel":393,"data":{"14":{"eligible":263,"right_haredi_pct":3.42,"center_left_arab_pct":96.58,"right_pct":3.42,"haredi_pct":0.0,"center_pct":0.76,"left_pct":95.82,"arab_pct":0.0,"kosher_votes":263,"bzb":371,"voters":265,"disqualified":2,"turnout_pct":71.4},"15":{"eligible":251,"right_haredi_pct":2.79,"center_left_arab_pct":94.82,"right_pct":2.39,"haredi_pct":0.4,"center_pct":1.99,"left_pct":92.83,"arab_pct":0.0,"kosher_votes":251,"bzb":354,"voters":251,"disqualified":0,"turnout_pct":70.9},"16":{"eligible":210,"right_haredi_pct":3.81,"center_left_arab_pct":88.1,"right_pct":2.86,"haredi_pct":0.95,"center_pct":5.24,"left_pct":82.38,"arab_pct":0.48,"kosher_votes":210,"bzb":327,"voters":212,"disqualified":2,"turnout_pct":64.8},"17":{"eligible":217,"right_haredi_pct":0.46,"center_left_arab_pct":92.17,"right_pct":0.46,"haredi_pct":0.0,"center_pct":11.98,"left_pct":80.18,"arab_pct":0.0,"kosher_votes":217,"voters":219,"disqualified":2},"18":{"eligible":245,"right_haredi_pct":3.27,"center_left_arab_pct":94.69,"right_pct":2.45,"haredi_pct":0.82,"center_pct":23.27,"left_pct":71.02,"arab_pct":0.41,"kosher_votes":245,"bzb":361,"voters":247,"disqualified":2,"turnout_pct":68.4},"19":{"eligible":262,"right_haredi_pct":5.73,"center_left_arab_pct":87.79,"right_pct":5.73,"haredi_pct":0.0,"center_pct":9.92,"left_pct":77.1,"arab_pct":0.76,"kosher_votes":262,"bzb":388,"voters":264,"disqualified":2,"turnout_pct":68.0},"20":{"eligible":262,"right_haredi_pct":5.34,"center_left_arab_pct":93.89,"right_pct":4.96,"haredi_pct":0.38,"center_pct":13.74,"left_pct":79.77,"arab_pct":0.38,"kosher_votes":262,"bzb":388,"voters":264,"disqualified":2,"turnout_pct":68.0},"21":{"eligible":310,"right_haredi_pct":8.06,"center_left_arab_pct":91.94,"right_pct":8.06,"haredi_pct":0.0,"center_pct":47.09,"left_pct":43.87,"arab_pct":0.0,"opposition_right_pct":0.97,"kosher_votes":310,"bzb":449,"voters":310,"disqualified":0,"turnout_pct":69.0},"22":{"eligible":318,"right_haredi_pct":3.77,"center_left_arab_pct":96.23,"right_pct":3.46,"haredi_pct":0.31,"center_pct":52.51,"left_pct":41.82,"arab_pct":0.0,"opposition_right_pct":1.89,"bzb":456,"voters":318,"kosher_votes":318,"disqualified":0,"turnout_pct":69.7},"23":{"eligible":326,"right_haredi_pct":4.29,"center_left_arab_pct":95.71,"right_pct":3.99,"haredi_pct":0.31,"center_pct":61.35,"left_pct":31.9,"arab_pct":1.23,"kosher_votes":326,"opposition_right_pct":1.23,"bzb":470,"voters":327,"disqualified":1,"turnout_pct":69.6},"24":{"eligible":326,"right_haredi_pct":2.15,"center_left_arab_pct":95.71,"right_pct":1.84,"haredi_pct":0.31,"center_pct":35.89,"left_pct":52.45,"arab_pct":0.0,"kosher_votes":326,"opposition_right_pct":7.36,"bzb":473,"voters":327,"disqualified":1,"turnout_pct":69.1},"25":{"eligible":337,"right_haredi_pct":3.86,"center_left_arab_pct":94.66,"right_pct":3.86,"haredi_pct":0.0,"center_pct":52.52,"left_pct":41.25,"arab_pct":0.3,"kosher_votes":337,"opposition_right_pct":0.59,"bzb":480,"voters":338,"disqualified":1,"turnout_pct":70.4},"13":{"eligible":244,"right_haredi_pct":0.82,"center_left_arab_pct":99.18,"right_pct":0.82,"haredi_pct":0.0,"center_pct":0.0,"left_pct":99.18,"arab_pct":0.0,"kosher_votes":244,"bzb":368,"voters":244,"disqualified":0,"turnout_pct":66.3}}}