{"he":"קדמת צבי","en":"Qidmat Zevi","semel":4025,"data":{"14":{"eligible":85,"right_haredi_pct":25.88,"center_left_arab_pct":74.12,"right_pct":25.88,"haredi_pct":0.0,"center_pct":51.76,"left_pct":22.35,"arab_pct":0.0,"kosher_votes":85,"bzb":95,"voters":85,"disqualified":0,"turnout_pct":89.5},"15":{"eligible":116,"right_haredi_pct":12.93,"center_left_arab_pct":86.21,"right_pct":11.21,"haredi_pct":1.72,"center_pct":50.0,"left_pct":36.21,"arab_pct":0.0,"kosher_votes":116,"bzb":127,"voters":116,"disqualified":0,"turnout_pct":91.3},"16":{"eligible":120,"right_haredi_pct":33.33,"center_left_arab_pct":60.83,"right_pct":33.33,"haredi_pct":0.0,"center_pct":25.83,"left_pct":35.0,"arab_pct":0.0,"kosher_votes":120,"bzb":188,"voters":120,"disqualified":0,"turnout_pct":63.8},"17":{"eligible":153,"right_haredi_pct":11.76,"center_left_arab_pct":73.2,"right_pct":11.11,"haredi_pct":0.65,"center_pct":45.75,"left_pct":26.8,"arab_pct":0.65,"kosher_votes":153,"voters":153,"disqualified":0},"18":{"eligible":173,"right_haredi_pct":32.37,"center_left_arab_pct":65.32,"right_pct":32.37,"haredi_pct":0.0,"center_pct":45.09,"left_pct":19.65,"arab_pct":0.58,"kosher_votes":173,"bzb":268,"voters":173,"disqualified":0,"turnout_pct":64.6},"19":{"eligible":197,"right_haredi_pct":22.34,"center_left_arab_pct":71.57,"right_pct":22.34,"haredi_pct":0.0,"center_pct":24.87,"left_pct":46.7,"arab_pct":0.0,"kosher_votes":197,"bzb":303,"voters":199,"disqualified":2,"turnout_pct":65.7},"20":{"eligible":221,"right_haredi_pct":27.15,"center_left_arab_pct":70.14,"right_pct":27.15,"haredi_pct":0.0,"center_pct":24.43,"left_pct":45.7,"arab_pct":0.0,"kosher_votes":221,"bzb":306,"voters":222,"disqualified":1,"turnout_pct":72.5},"21":{"eligible":290,"right_haredi_pct":24.83,"center_left_arab_pct":75.17,"right_pct":24.83,"haredi_pct":0.0,"center_pct":63.8,"left_pct":9.66,"arab_pct":0.0,"opposition_right_pct":1.72,"kosher_votes":290,"bzb":372,"voters":290,"disqualified":0,"turnout_pct":78.0},"22":{"eligible":262,"right_haredi_pct":21.37,"center_left_arab_pct":76.34,"right_pct":20.99,"haredi_pct":0.38,"center_pct":58.4,"left_pct":13.36,"arab_pct":0.0,"opposition_right_pct":4.58,"bzb":380,"voters":267,"kosher_votes":262,"disqualified":5,"turnout_pct":70.3},"23":{"eligible":282,"right_haredi_pct":27.3,"center_left_arab_pct":72.34,"right_pct":26.95,"haredi_pct":0.35,"center_pct":55.32,"left_pct":12.77,"arab_pct":0.0,"kosher_votes":282,"opposition_right_pct":4.26,"bzb":392,"voters":283,"disqualified":1,"turnout_pct":72.2},"24":{"eligible":298,"right_haredi_pct":19.8,"center_left_arab_pct":76.17,"right_pct":19.8,"haredi_pct":0.0,"center_pct":35.23,"left_pct":21.48,"arab_pct":0.34,"kosher_votes":298,"opposition_right_pct":19.13,"bzb":406,"voters":298,"disqualified":0,"turnout_pct":73.4},"25":{"eligible":291,"right_haredi_pct":30.24,"center_left_arab_pct":65.98,"right_pct":29.9,"haredi_pct":0.34,"center_pct":53.95,"left_pct":11.0,"arab_pct":0.0,"kosher_votes":291,"opposition_right_pct":1.03,"bzb":431,"voters":294,"disqualified":3,"turnout_pct":68.2}}}