{"he":"ג'ש )גוש חלב(","en":"Jish(Gush Halav)","semel":487,"data":{"14":{"eligible":1155,"right_haredi_pct":2.34,"center_left_arab_pct":94.81,"right_pct":1.3,"haredi_pct":1.04,"center_pct":0.09,"left_pct":41.73,"arab_pct":52.99,"kosher_votes":1155,"bzb":1600,"voters":1186,"disqualified":31,"turnout_pct":74.1},"15":{"eligible":1344,"right_haredi_pct":7.37,"center_left_arab_pct":90.25,"right_pct":5.73,"haredi_pct":1.64,"center_pct":5.43,"left_pct":17.11,"arab_pct":67.71,"kosher_votes":1344,"bzb":1781,"voters":1385,"disqualified":41,"turnout_pct":77.8},"16":{"eligible":1058,"right_haredi_pct":10.68,"center_left_arab_pct":88.09,"right_pct":8.79,"haredi_pct":1.89,"center_pct":0.09,"left_pct":36.67,"arab_pct":51.32,"kosher_votes":1058,"bzb":1886,"voters":1076,"disqualified":18,"turnout_pct":57.1},"18":{"eligible":705,"right_haredi_pct":5.25,"center_left_arab_pct":93.33,"right_pct":4.96,"haredi_pct":0.28,"center_pct":17.16,"left_pct":10.07,"arab_pct":66.1,"kosher_votes":705,"bzb":2043,"voters":729,"disqualified":24,"turnout_pct":35.7},"19":{"eligible":958,"right_haredi_pct":16.39,"center_left_arab_pct":81.94,"right_pct":11.17,"haredi_pct":5.22,"center_pct":3.44,"left_pct":21.82,"arab_pct":56.68,"kosher_votes":958,"bzb":2208,"voters":981,"disqualified":23,"turnout_pct":44.4},"20":{"eligible":1360,"right_haredi_pct":13.46,"center_left_arab_pct":85.44,"right_pct":11.99,"haredi_pct":1.47,"center_pct":1.76,"left_pct":14.19,"arab_pct":69.49,"kosher_votes":1360,"bzb":2309,"voters":1374,"disqualified":14,"turnout_pct":59.5},"21":{"eligible":1135,"right_haredi_pct":4.32,"center_left_arab_pct":94.19,"right_pct":0.88,"haredi_pct":3.44,"center_pct":29.96,"left_pct":10.13,"arab_pct":54.1,"opposition_right_pct":0,"kosher_votes":1135,"bzb":2438,"voters":1153,"disqualified":18,"turnout_pct":47.3},"22":{"eligible":1454,"right_haredi_pct":1.44,"center_left_arab_pct":97.04,"right_pct":0.89,"haredi_pct":0.55,"center_pct":28.89,"left_pct":5.43,"arab_pct":62.72,"opposition_right_pct":0,"kosher_votes":1454,"bzb":2447,"voters":1472,"disqualified":18,"turnout_pct":60.2},"23":{"eligible":1513,"right_haredi_pct":1.19,"center_left_arab_pct":98.22,"right_pct":0.86,"haredi_pct":0.33,"center_pct":7.07,"left_pct":3.57,"arab_pct":73.96,"opposition_right_pct":13.62,"kosher_votes":1513,"bzb":2459,"voters":1527,"disqualified":14,"turnout_pct":62.1},"24":{"eligible":1112,"right_haredi_pct":13.31,"center_left_arab_pct":85.88,"right_pct":13.31,"haredi_pct":0.0,"center_pct":5.4,"left_pct":13.76,"arab_pct":66.19,"kosher_votes":1112,"opposition_right_pct":0.54,"bzb":2501,"voters":1131,"disqualified":19,"turnout_pct":45.2},"25":{"eligible":1263,"right_haredi_pct":3.56,"center_left_arab_pct":95.25,"right_pct":3.17,"haredi_pct":0.4,"center_pct":9.34,"left_pct":11.72,"arab_pct":74.11,"kosher_votes":1263,"opposition_right_pct":0.08,"bzb":2563,"voters":1271,"disqualified":8,"turnout_pct":49.6}}}