{"he":"תרום","en":"Tarum","semel":778,"data":{"14":{"eligible":258,"right_haredi_pct":98.45,"center_left_arab_pct":1.16,"right_pct":78.29,"haredi_pct":20.16,"center_pct":0.0,"left_pct":1.16,"arab_pct":0.0,"kosher_votes":258,"bzb":288,"voters":259,"disqualified":1,"turnout_pct":89.9},"15":{"eligible":268,"right_haredi_pct":92.91,"center_left_arab_pct":5.22,"right_pct":54.48,"haredi_pct":38.43,"center_pct":2.24,"left_pct":2.99,"arab_pct":0.0,"kosher_votes":268,"bzb":300,"voters":272,"disqualified":4,"turnout_pct":90.7},"16":{"eligible":259,"right_haredi_pct":94.98,"center_left_arab_pct":3.47,"right_pct":72.59,"haredi_pct":22.39,"center_pct":1.16,"left_pct":1.93,"arab_pct":0.39,"kosher_votes":259,"bzb":330,"voters":265,"disqualified":6,"turnout_pct":80.3},"17":{"eligible":236,"right_haredi_pct":81.78,"center_left_arab_pct":13.98,"right_pct":57.63,"haredi_pct":24.15,"center_pct":11.44,"left_pct":1.69,"arab_pct":0.85,"kosher_votes":236,"voters":238,"disqualified":2},"18":{"eligible":263,"right_haredi_pct":90.49,"center_left_arab_pct":8.37,"right_pct":67.3,"haredi_pct":23.19,"center_pct":5.32,"left_pct":3.04,"arab_pct":0.0,"kosher_votes":263,"bzb":362,"voters":266,"disqualified":3,"turnout_pct":73.5},"19":{"eligible":304,"right_haredi_pct":80.59,"center_left_arab_pct":9.54,"right_pct":64.14,"haredi_pct":16.45,"center_pct":2.96,"left_pct":6.58,"arab_pct":0.0,"kosher_votes":304,"bzb":401,"voters":306,"disqualified":2,"turnout_pct":76.3},"20":{"eligible":409,"right_haredi_pct":83.13,"center_left_arab_pct":15.16,"right_pct":67.24,"haredi_pct":15.89,"center_pct":9.54,"left_pct":5.62,"arab_pct":0.0,"kosher_votes":409,"bzb":482,"voters":411,"disqualified":2,"turnout_pct":85.3},"21":{"eligible":440,"right_haredi_pct":87.5,"center_left_arab_pct":12.5,"right_pct":78.41,"haredi_pct":9.09,"center_pct":10.68,"left_pct":1.82,"arab_pct":0.0,"opposition_right_pct":0.0,"kosher_votes":440,"bzb":556,"voters":441,"disqualified":1,"turnout_pct":79.3},"22":{"eligible":452,"right_haredi_pct":78.76,"center_left_arab_pct":12.83,"right_pct":66.15,"haredi_pct":12.61,"center_pct":7.75,"left_pct":4.65,"arab_pct":0.0,"opposition_right_pct":0.44,"bzb":565,"voters":452,"kosher_votes":452,"disqualified":0,"turnout_pct":80.0},"23":{"eligible":471,"right_haredi_pct":83.86,"center_left_arab_pct":15.92,"right_pct":72.4,"haredi_pct":11.46,"center_pct":13.8,"left_pct":1.91,"arab_pct":0.0,"kosher_votes":471,"opposition_right_pct":0.21,"bzb":576,"voters":472,"disqualified":1,"turnout_pct":81.9},"24":{"eligible":468,"right_haredi_pct":66.67,"center_left_arab_pct":31.2,"right_pct":56.62,"haredi_pct":10.04,"center_pct":6.2,"left_pct":1.92,"arab_pct":0.0,"kosher_votes":468,"opposition_right_pct":23.08,"bzb":592,"voters":468,"disqualified":0,"turnout_pct":79.1},"25":{"eligible":494,"right_haredi_pct":82.79,"center_left_arab_pct":14.98,"right_pct":70.45,"haredi_pct":12.35,"center_pct":13.56,"left_pct":1.21,"arab_pct":0.2,"kosher_votes":494,"opposition_right_pct":0.0,"bzb":616,"voters":494,"disqualified":0,"turnout_pct":80.2},"13":{"eligible":247,"right_haredi_pct":92.31,"center_left_arab_pct":2.83,"right_pct":76.92,"haredi_pct":15.38,"center_pct":0.0,"left_pct":2.83,"arab_pct":0.0,"kosher_votes":247,"bzb":271,"voters":248,"disqualified":1,"turnout_pct":91.5}}}