{"he":"קרית מוצקין","en":"Kiryat Motzkin","semel":8200,"data":{"14":{"eligible":20422,"right_haredi_pct":50.48,"center_left_arab_pct":47.18,"right_pct":45.4,"haredi_pct":5.08,"center_pct":4.13,"left_pct":42.98,"arab_pct":0.07,"kosher_votes":20422,"bzb":26820,"voters":20927,"disqualified":505,"turnout_pct":78.0},"15":{"eligible":22759,"right_haredi_pct":40.49,"center_left_arab_pct":52.33,"right_pct":31.0,"haredi_pct":9.48,"center_pct":14.57,"left_pct":37.66,"arab_pct":0.11,"kosher_votes":22759,"bzb":30156,"voters":23280,"disqualified":521,"turnout_pct":77.2},"16":{"eligible":20932,"right_haredi_pct":53.06,"center_left_arab_pct":44.61,"right_pct":48.36,"haredi_pct":4.7,"center_pct":18.41,"left_pct":26.04,"arab_pct":0.15,"kosher_votes":20932,"bzb":33012,"voters":21318,"disqualified":386,"turnout_pct":64.6},"17":{"eligible":20451,"right_haredi_pct":32.0,"center_left_arab_pct":62.57,"right_pct":26.14,"haredi_pct":5.86,"center_pct":42.73,"left_pct":19.75,"arab_pct":0.09,"kosher_votes":20451,"voters":20772,"disqualified":321},"18":{"eligible":21656,"right_haredi_pct":50.51,"center_left_arab_pct":47.64,"right_pct":46.26,"haredi_pct":4.26,"center_pct":33.47,"left_pct":13.94,"arab_pct":0.23,"kosher_votes":21656,"bzb":34365,"voters":22032,"disqualified":376,"turnout_pct":64.1},"19":{"eligible":21942,"right_haredi_pct":43.69,"center_left_arab_pct":50.0,"right_pct":39.41,"haredi_pct":4.27,"center_pct":24.0,"left_pct":25.91,"arab_pct":0.1,"kosher_votes":21942,"bzb":34909,"voters":22221,"disqualified":279,"turnout_pct":63.7},"20":{"eligible":24233,"right_haredi_pct":46.84,"center_left_arab_pct":51.68,"right_pct":43.14,"haredi_pct":3.7,"center_pct":26.34,"left_pct":25.27,"arab_pct":0.07,"kosher_votes":24233,"bzb":35487,"voters":24495,"disqualified":262,"turnout_pct":69.0},"21":{"eligible":24712,"right_haredi_pct":48.83,"center_left_arab_pct":50.18,"right_pct":46.54,"haredi_pct":2.29,"center_pct":37.09,"left_pct":5.43,"arab_pct":0.08,"opposition_right_pct":7.58,"kosher_votes":24712,"bzb":37178,"voters":24868,"disqualified":156,"turnout_pct":66.9},"22":{"eligible":24493,"right_haredi_pct":41.59,"center_left_arab_pct":57.88,"right_pct":37.84,"haredi_pct":3.75,"center_pct":36.59,"left_pct":7.8,"arab_pct":0.06,"opposition_right_pct":13.43,"bzb":37610,"voters":24680,"kosher_votes":24493,"disqualified":187,"turnout_pct":65.6},"23":{"eligible":24675,"right_haredi_pct":46.67,"center_left_arab_pct":52.9,"right_pct":43.02,"haredi_pct":3.65,"center_pct":37.28,"left_pct":4.37,"arab_pct":0.12,"kosher_votes":24675,"opposition_right_pct":11.12,"bzb":37981,"voters":24829,"disqualified":154,"turnout_pct":65.4},"24":{"eligible":24272,"right_haredi_pct":37.01,"center_left_arab_pct":61.26,"right_pct":33.95,"haredi_pct":3.06,"center_pct":29.62,"left_pct":6.72,"arab_pct":0.07,"kosher_votes":24272,"opposition_right_pct":24.84,"bzb":39426,"voters":24409,"disqualified":137,"turnout_pct":61.9},"25":{"eligible":25775,"right_haredi_pct":46.6,"center_left_arab_pct":51.61,"right_pct":42.88,"haredi_pct":3.72,"center_pct":39.94,"left_pct":3.86,"arab_pct":0.1,"kosher_votes":25775,"opposition_right_pct":7.71,"bzb":40960,"voters":25947,"disqualified":172,"turnout_pct":63.3},"13":{"eligible":18800,"right_haredi_pct":41.26,"center_left_arab_pct":56.65,"right_pct":38.99,"haredi_pct":2.27,"center_pct":0.0,"left_pct":56.6,"arab_pct":0.05,"kosher_votes":18800,"bzb":24343,"voters":18894,"disqualified":94,"turnout_pct":77.6}}}