{"he":"פתחיה","en":"Petahya","semel":839,"data":{"14":{"eligible":318,"right_haredi_pct":72.64,"center_left_arab_pct":26.42,"right_pct":66.67,"haredi_pct":5.97,"center_pct":2.52,"left_pct":23.9,"arab_pct":0.0,"kosher_votes":318,"bzb":405,"voters":330,"disqualified":12,"turnout_pct":81.5},"15":{"eligible":319,"right_haredi_pct":67.08,"center_left_arab_pct":28.21,"right_pct":47.96,"haredi_pct":19.12,"center_pct":12.54,"left_pct":15.67,"arab_pct":0.0,"kosher_votes":319,"bzb":414,"voters":321,"disqualified":2,"turnout_pct":77.5},"16":{"eligible":321,"right_haredi_pct":82.24,"center_left_arab_pct":15.89,"right_pct":75.7,"haredi_pct":6.54,"center_pct":5.61,"left_pct":10.28,"arab_pct":0.0,"kosher_votes":321,"bzb":467,"voters":322,"disqualified":1,"turnout_pct":69.0},"17":{"eligible":304,"right_haredi_pct":44.74,"center_left_arab_pct":49.67,"right_pct":29.28,"haredi_pct":15.46,"center_pct":37.17,"left_pct":12.17,"arab_pct":0.33,"kosher_votes":304,"voters":307,"disqualified":3},"18":{"eligible":391,"right_haredi_pct":63.43,"center_left_arab_pct":34.53,"right_pct":53.2,"haredi_pct":10.23,"center_pct":26.34,"left_pct":7.93,"arab_pct":0.26,"kosher_votes":391,"bzb":564,"voters":393,"disqualified":2,"turnout_pct":69.7},"19":{"eligible":429,"right_haredi_pct":54.55,"center_left_arab_pct":41.72,"right_pct":42.42,"haredi_pct":12.12,"center_pct":25.41,"left_pct":16.32,"arab_pct":0.0,"kosher_votes":429,"bzb":610,"voters":437,"disqualified":8,"turnout_pct":71.6},"20":{"eligible":494,"right_haredi_pct":51.82,"center_left_arab_pct":47.77,"right_pct":43.32,"haredi_pct":8.5,"center_pct":30.16,"left_pct":17.61,"arab_pct":0.0,"kosher_votes":494,"bzb":633,"voters":495,"disqualified":1,"turnout_pct":78.2},"21":{"eligible":485,"right_haredi_pct":62.27,"center_left_arab_pct":37.11,"right_pct":56.91,"haredi_pct":5.36,"center_pct":33.4,"left_pct":3.3,"arab_pct":0.0,"opposition_right_pct":0.41,"kosher_votes":485,"bzb":616,"voters":487,"disqualified":2,"turnout_pct":79.1},"22":{"eligible":478,"right_haredi_pct":48.54,"center_left_arab_pct":28.66,"right_pct":41.42,"haredi_pct":7.11,"center_pct":21.34,"left_pct":5.86,"arab_pct":0.0,"opposition_right_pct":1.46,"bzb":612,"voters":480,"kosher_votes":478,"disqualified":2,"turnout_pct":78.4},"23":{"eligible":478,"right_haredi_pct":66.11,"center_left_arab_pct":33.89,"right_pct":59.0,"haredi_pct":7.11,"center_pct":28.87,"left_pct":3.14,"arab_pct":0.0,"kosher_votes":478,"opposition_right_pct":1.88,"bzb":612,"voters":482,"disqualified":4,"turnout_pct":78.8},"24":{"eligible":466,"right_haredi_pct":54.51,"center_left_arab_pct":42.92,"right_pct":46.57,"haredi_pct":7.94,"center_pct":22.32,"left_pct":3.65,"arab_pct":0.0,"kosher_votes":466,"opposition_right_pct":16.95,"bzb":618,"voters":468,"disqualified":2,"turnout_pct":75.7},"25":{"eligible":504,"right_haredi_pct":65.67,"center_left_arab_pct":32.94,"right_pct":57.34,"haredi_pct":8.33,"center_pct":28.97,"left_pct":2.78,"arab_pct":0.4,"kosher_votes":504,"opposition_right_pct":0.79,"bzb":639,"voters":504,"disqualified":0,"turnout_pct":78.9},"13":{"eligible":262,"right_haredi_pct":73.28,"center_left_arab_pct":26.34,"right_pct":68.32,"haredi_pct":4.96,"center_pct":0.0,"left_pct":26.34,"arab_pct":0.0,"kosher_votes":262,"bzb":357,"voters":263,"disqualified":1,"turnout_pct":73.7}}}