{"he":"ישע","en":"Yesha","semel":916,"data":{"14":{"eligible":121,"right_haredi_pct":24.79,"center_left_arab_pct":75.21,"right_pct":22.31,"haredi_pct":2.48,"center_pct":4.96,"left_pct":70.25,"arab_pct":0.0,"kosher_votes":121,"bzb":166,"voters":122,"disqualified":1,"turnout_pct":73.5},"15":{"eligible":131,"right_haredi_pct":21.37,"center_left_arab_pct":73.28,"right_pct":16.79,"haredi_pct":4.58,"center_pct":19.85,"left_pct":53.44,"arab_pct":0.0,"kosher_votes":131,"bzb":171,"voters":133,"disqualified":2,"turnout_pct":77.8},"16":{"eligible":105,"right_haredi_pct":46.67,"center_left_arab_pct":50.48,"right_pct":44.76,"haredi_pct":1.9,"center_pct":11.43,"left_pct":39.05,"arab_pct":0.0,"kosher_votes":105,"bzb":163,"voters":106,"disqualified":1,"turnout_pct":65.0},"17":{"eligible":128,"right_haredi_pct":19.53,"center_left_arab_pct":71.88,"right_pct":14.84,"haredi_pct":4.69,"center_pct":29.69,"left_pct":42.19,"arab_pct":0.0,"kosher_votes":128,"voters":129,"disqualified":1},"18":{"eligible":147,"right_haredi_pct":36.05,"center_left_arab_pct":62.59,"right_pct":34.69,"haredi_pct":1.36,"center_pct":42.18,"left_pct":19.73,"arab_pct":0.68,"kosher_votes":147,"bzb":203,"voters":149,"disqualified":2,"turnout_pct":73.4},"19":{"eligible":169,"right_haredi_pct":33.14,"center_left_arab_pct":57.99,"right_pct":31.95,"haredi_pct":1.18,"center_pct":22.49,"left_pct":35.5,"arab_pct":0.0,"kosher_votes":169,"bzb":240,"voters":170,"disqualified":1,"turnout_pct":70.8},"20":{"eligible":188,"right_haredi_pct":36.7,"center_left_arab_pct":61.7,"right_pct":35.64,"haredi_pct":1.06,"center_pct":20.21,"left_pct":41.49,"arab_pct":0.0,"kosher_votes":188,"bzb":260,"voters":189,"disqualified":1,"turnout_pct":72.7},"21":{"eligible":201,"right_haredi_pct":39.8,"center_left_arab_pct":58.71,"right_pct":39.8,"haredi_pct":0.0,"center_pct":39.8,"left_pct":17.41,"arab_pct":0.0,"opposition_right_pct":1.49,"kosher_votes":201,"bzb":275,"voters":202,"disqualified":1,"turnout_pct":73.5},"22":{"eligible":205,"right_haredi_pct":31.22,"center_left_arab_pct":59.51,"right_pct":30.24,"haredi_pct":0.98,"center_pct":38.05,"left_pct":16.59,"arab_pct":0.0,"opposition_right_pct":4.88,"bzb":280,"voters":210,"kosher_votes":205,"disqualified":5,"turnout_pct":75.0},"23":{"eligible":198,"right_haredi_pct":43.43,"center_left_arab_pct":55.56,"right_pct":43.43,"haredi_pct":0.0,"center_pct":39.9,"left_pct":13.13,"arab_pct":0.0,"kosher_votes":198,"opposition_right_pct":2.53,"bzb":279,"voters":198,"disqualified":0,"turnout_pct":71.0},"24":{"eligible":191,"right_haredi_pct":36.65,"center_left_arab_pct":61.26,"right_pct":35.6,"haredi_pct":1.05,"center_pct":28.8,"left_pct":17.28,"arab_pct":0.0,"kosher_votes":191,"opposition_right_pct":15.18,"bzb":296,"voters":192,"disqualified":1,"turnout_pct":64.9},"25":{"eligible":215,"right_haredi_pct":47.44,"center_left_arab_pct":50.7,"right_pct":45.58,"haredi_pct":1.86,"center_pct":41.86,"left_pct":8.37,"arab_pct":0.0,"kosher_votes":215,"opposition_right_pct":0.47,"bzb":301,"voters":216,"disqualified":1,"turnout_pct":71.8},"13":{"eligible":109,"right_haredi_pct":18.35,"center_left_arab_pct":81.65,"right_pct":18.35,"haredi_pct":0.0,"center_pct":0.0,"left_pct":81.65,"arab_pct":0.0,"kosher_votes":109,"bzb":156,"voters":109,"disqualified":0,"turnout_pct":69.9}}}