{"he":"יהוד-מונוסון","en":"Yehud-Monosson","semel":9400,"data":{"18":{"eligible":14010,"right_haredi_pct":46.97,"center_left_arab_pct":51.31,"right_pct":39.98,"haredi_pct":6.99,"center_pct":34.2,"left_pct":16.94,"arab_pct":0.17,"kosher_votes":14010,"bzb":20438,"voters":14173,"disqualified":163,"turnout_pct":69.3},"19":{"eligible":15556,"right_haredi_pct":40.54,"center_left_arab_pct":53.22,"right_pct":34.33,"haredi_pct":6.22,"center_pct":27.32,"left_pct":25.76,"arab_pct":0.14,"kosher_votes":15556,"bzb":21444,"voters":15687,"disqualified":131,"turnout_pct":73.2},"20":{"eligible":16614,"right_haredi_pct":42.73,"center_left_arab_pct":55.62,"right_pct":37.46,"haredi_pct":5.27,"center_pct":24.97,"left_pct":30.56,"arab_pct":0.08,"kosher_votes":16614,"bzb":21985,"voters":16725,"disqualified":111,"turnout_pct":76.1},"21":{"eligible":17137,"right_haredi_pct":48.9,"center_left_arab_pct":50.64,"right_pct":45.38,"haredi_pct":3.52,"center_pct":41.69,"left_pct":7.49,"arab_pct":0.09,"opposition_right_pct":1.37,"kosher_votes":17137,"bzb":23080,"voters":17210,"disqualified":73,"turnout_pct":74.6},"22":{"eligible":17101,"right_haredi_pct":44.23,"center_left_arab_pct":55.26,"right_pct":39.25,"haredi_pct":4.98,"center_pct":40.43,"left_pct":10.23,"arab_pct":0.1,"opposition_right_pct":4.5,"bzb":23181,"voters":17160,"kosher_votes":17101,"disqualified":59,"turnout_pct":74.0},"14":{"eligible":12750,"right_haredi_pct":55.7,"center_left_arab_pct":42.92,"right_pct":45.22,"haredi_pct":10.47,"center_pct":4.88,"left_pct":37.93,"arab_pct":0.11,"kosher_votes":12750,"bzb":15787,"voters":12947,"disqualified":197,"opposition_right_pct":0,"turnout_pct":82.0},"15":{"eligible":14005,"right_haredi_pct":42.52,"center_left_arab_pct":51.68,"right_pct":29.79,"haredi_pct":12.72,"center_pct":15.43,"left_pct":36.02,"arab_pct":0.24,"kosher_votes":14005,"bzb":17287,"voters":14193,"disqualified":188,"opposition_right_pct":0,"turnout_pct":82.1},"16":{"eligible":13239,"right_haredi_pct":55.01,"center_left_arab_pct":42.75,"right_pct":47.41,"haredi_pct":7.6,"center_pct":16.27,"left_pct":26.38,"arab_pct":0.1,"kosher_votes":13239,"bzb":18776,"voters":13413,"disqualified":174,"opposition_right_pct":0,"turnout_pct":71.4},"17":{"right_haredi_pct":30.46,"center_left_arab_pct":63.78,"right_pct":21.92,"haredi_pct":8.54,"center_pct":43.17,"left_pct":20.49,"arab_pct":0.12,"opposition_right_pct":0,"eligible":12941,"kosher_votes":12941,"bzb":0,"voters":13087,"disqualified":146},"23":{"eligible":16825,"right_haredi_pct":49.04,"center_left_arab_pct":50.72,"right_pct":43.75,"haredi_pct":5.29,"center_pct":41.58,"left_pct":5.95,"arab_pct":0.19,"kosher_votes":16825,"opposition_right_pct":3.0,"bzb":23179,"voters":16902,"disqualified":77,"turnout_pct":72.9},"24":{"eligible":16730,"right_haredi_pct":38.91,"center_left_arab_pct":59.38,"right_pct":34.81,"haredi_pct":4.11,"center_pct":33.29,"left_pct":10.81,"arab_pct":0.04,"kosher_votes":16730,"opposition_right_pct":15.25,"bzb":23405,"voters":16789,"disqualified":59,"turnout_pct":71.7},"25":{"eligible":17966,"right_haredi_pct":48.03,"center_left_arab_pct":50.37,"right_pct":43.16,"haredi_pct":4.86,"center_pct":41.53,"left_pct":6.17,"arab_pct":0.14,"kosher_votes":17966,"opposition_right_pct":2.52,"bzb":24273,"voters":18028,"disqualified":62,"turnout_pct":74.3}}}