{"חיפה|הקונגרס,43": [32.8345473, 35.0567863], "נצרת|ש פועלי נצרת": null, "נצרת|כרם א-סאחב": [32.7099467, 35.28453], "נצרת|כרם אל-ג'מאל": [32.7145779, 35.2936886], "נצרת|רח 4021,30": null, "נתניה|בן אליעזר,35": [32.3203853, 34.8577964], "טירה|שכונה מזרחית": null, "נצרת|חאלת א-דיר,22": null, "כפר קאסם|א שוהדא": [32.1158698, 34.9721808], "קרית ביאליק|אפרים,28": [32.8286854, 35.0820115], "שפרעם|מרכז מסחר-ע עתיקה,1": null, "תל אביב - יפו|הנגרים,23": [32.056585, 34.765162], "כפר קרע|אלחווארנה": [32.505738, 35.045173], "נצרת|רח 5097,16": null, "ירושלים|כט' בנובמבר,13": null, "תל אביב - יפו|מולדת,4": [32.05564, 34.773205], "אשקלון|גרופר יעקב,18": [31.662749, 34.565406], "רהט|אלנג'אח": [31.384976, 34.736932], "תל אביב - יפו|הר נבו,19": [32.090061, 34.781506], "רהט|אלפרדוס": null, "תל אביב - יפו|אד\"ם הכהן,5": [32.085045, 34.776926], "חריש|סביון,16": [32.456551, 35.053115], "תל אביב - יפו|מנדלי מוכר ספרים,19": [32.079242, 34.771706], "אשקלון|מעלה הגת,19": [31.6920915, 34.5783532], "ראש העין|יפה ירקוני,9": [32.0875374, 34.9769634], "תל אביב - יפו|שפירא צבי,21": [32.075491, 34.778113], "נתניה|שמורת נחל שניר,3": [32.2884771, 34.8510335], "חדרה|הגבורים": null, "חריש|רימון,8": [32.4586398, 35.0449691], "תל אביב - יפו|בני אפרים,228": [32.117361, 34.818231], "פתח תקווה|מנחת שלמה,1": [32.0693361, 34.9124919], "תל אביב - יפו|בורלא יהודה,25": [32.1081362, 34.7903739], "ירושלים|סורוצקין,46": [31.7968888, 35.2058624], "פתח תקווה|הרב משורר ישעיהו,27": [32.0693242, 34.9050791], "עפולה|האגס,4": [32.6185924, 35.2871992], "גני תקווה|דרך המלך,6": [32.0656463, 34.8727758], "תל אביב - יפו|זינגר בשביס יצחק,3": [32.113688, 34.785519], "תל אביב - יפו|דיזנגוף,221": [32.089807, 34.775454], "ראשון לציון|הגדוד העברי,17": [31.9638036, 34.8104646], "ראש העין|שבזי,182": [32.0986533, 34.9419106], "תל אביב - יפו|שד' ששת הימים,26": null, "רחובות|שטינברג,10": null, "ראשון לציון|נורדאו,55": [31.9587228, 34.8077882], "ראשון לציון|אלקבץ,2": [31.9784045, 34.7734465], "נתיבות|קטיף,82": [31.4193433, 34.5725606], "אשדוד|העצמאות,63": [31.7901332, 34.6468172], "אשדוד|אליעזר בן הורקנוס,18": [31.7908887, 34.6605642], "גבעת שמואל|בגין מנחם,2": [32.0739741, 34.853446], "תל אביב - יפו|אשכול לוי,94": [32.1145128, 34.7899584], "חולון|רבין יצחק,20": [32.0027281, 34.7706063], "באר שבע|בורג יוסף,33": [31.2333905, 34.769528], "חולון|ביאליק,21": [32.0078044, 34.77072], "רחובות|הרב הרצוג,16": [31.9031115, 34.8151206], "פתח תקווה|מרדכי בצ'איב": null, "פתח תקווה|הרב אונטרמן,14": [32.099596, 34.8992377], "פתח תקווה|ישעיהו ישראל,12": [32.0790194, 34.8993399], "הרצליה|ז'בוטינסקי,3": [32.1643191, 34.8280018], "נתניה|מעפילי אגוז,5": [32.273566, 34.8470173], "רחובות|מרשוב,3": [31.8936869, 34.8055174], "רחובות|נורדאו,20": [31.8944152, 34.815363], "ירושלים|תירוש,9": [31.7352056, 35.1808988], "חולון|אילון פנחס,20": [32.0082506, 34.7798849], "חולון|קפלן,17": [32.018378, 34.8084363], "ראשון לציון|ראובן ובת שבע,4": [31.9707353, 34.8155301], "ראשון לציון|ש נווה דקלים,54": [31.9808927, 34.7559856], "תל אביב - יפו|קובנר אבא,16": [32.101355, 34.785668], "תל אביב - יפו|שפרינצק,4": [32.0712316, 34.7840821], "ירושלים|בית\"ר,8": [31.7533085, 35.2244688], "רחובות|מילר טובה וטוביה,10": [31.9003504, 34.8187491], "ראשון לציון|העצמאות,37": [31.9814762, 34.8005564], "אשדוד|תפוז,5": [31.7687352, 34.6366546], "בני ברק|קהילות יעקב,65": [32.0712458, 34.8385563], "גבעת שמואל|ביאליק,59": [32.077594, 34.8494224], "ראשון לציון|מעגל השלום,2": [31.9698396, 34.7668651], "בני ברק|אשל אברהם,17": [32.0825465, 34.8426066], "באר יעקב|שוהם": [31.9356923, 34.8240266], "ביתר עילית|אלעזר המודעי,23": null, "טירת כרמל|עוגן,14": null, "מודיעין עילית|נתיבות המשפט,5": null, "אשדוד|רב ינאי,3": [31.7868081, 34.6674331], "תל אביב - יפו|מודיליאני,19": [32.080835, 34.784934], "הוד השרון|משאבים,46": [32.1576762, 34.8901679], "בני ברק|רמב\"ם,22": [32.0893322, 34.8294403], "קרית אונו|רבין יצחק,11": [32.0641438, 34.8612783], "אלעד|רבי יונתן בן עוזיאל,19": null, "תל אביב - יפו|עמק ברכה,48א": [32.0753618, 34.800762], "רחובות|אחים קיבוביץ": null, "חריש|ברקת,13": [32.4670203, 35.0448023], "פתח תקווה|רום יעל,10": [32.1011984, 34.882038], "ירושלים|ויטל חיים,32": [31.7892203, 35.191675], "פתח תקווה|עדש שפיק,7": null, "בני ברק|אהרונוביץ ראובן,31": null, "גבעתיים|צביה,5": [32.0639029, 34.8134287], "פתח תקווה|בן חור,14": [32.1059157, 34.8784249], "חולון|דרורי אמיר,3": [32.0068786, 34.7804531], "בני ברק|הרב סורוצקין,9": [32.0855403, 34.8421509], "באר שבע|רבקה,4": [31.2697755, 34.7624993], "בני ברק|דקר,12": [32.0791269, 34.8314194], "בנימינה-גבעת עדה|המורה": [32.519568, 34.9493861], "נס ציונה|לרר משה,29": [31.9277769, 34.7860704], "חולון|ברקן,18": [32.030336, 34.7631859], "באר יעקב|הדקל": [31.9389277, 34.8343318], "חיפה|בן צבי יצחק,6": [32.7523214, 34.9716721], "פתח תקווה|העצמאות,50": [32.0749495, 34.8771352], "מודיעין עילית|רש\"י,2": null, "חולון|ההסתדרות,20": [32.0177518, 34.7685083], "באר שבע|ככר הגנים,16": [31.2302602, 34.789271], "אשקלון|שד' הציונות": [31.68562, 34.580371], "פרדס חנה-כרכור|צליל,7": null, "אשדוד|חטיבת הנגב,30": [31.8019409, 34.6640555], "פתח תקווה|עדש שפיק,2": null, "גבעתיים|הכנסת,4": [32.0705688, 34.8124667], "תל אביב - יפו|בקר אהרון,10": [32.122269, 34.817092], "בת ים|בר אילן,73": [32.0116695, 34.7427459], "גבעתיים|ריינס,2": [32.0683924, 34.8086704], "ראשון לציון|היין,2": [31.9736577, 34.7774539], "חולון|שער ציון,9": [32.0096158, 34.7878968], "כפר סבא|ספיר,20": [32.1972995, 34.8902785], "ראשון לציון|ירמיהו,11": [31.9518244, 34.8161157], "מיתר|שדרות עומרים,1": [31.3287728, 34.9398872], "גן יבנה|דרך יצחק רבין,2": null, "אלעד|רבי יהושע,3": [32.0560234, 34.9580433], "ראשון לציון|צמח,7": [31.9703436, 34.7941212], "תל אביב - יפו|ביל\"ו,17": [32.06945, 34.779866], "רחובות|פרופ' נאמן יובל,106": [31.9021343, 34.8243136], "בני ברק|המר זבולון,2": [32.0895765, 34.8431379], "זכרון יעקב|שד ניל\"י": [32.5699667, 34.9425213], "ירושלים|מגן האלף,3": [31.7948537, 35.2230044], "ביתר עילית|פחד יצחק,30": null, "הוד השרון|גולדה מאיר,9": [32.1681178, 34.9004146], "נתניה|החפץ חיים,801": [32.2953873, 34.8453048], "מודיעין עילית|נתיבות המשפט,111": [31.9339485, 35.0471955], "ירושלים|נטר,1": [31.7989198, 35.2251026], "ראשון לציון|מבצע משה,39": [31.9825773, 34.7825583], "בת ים|השקמה,28": [32.0137412, 34.7442187], "ירושלים|נדבה יוסף,47": [31.815312, 35.2524963], "בני ברק|עזרא,53": [32.0756365, 34.8352529], "תל אביב - יפו|קהילת ורשה,30": [32.111637, 34.819863], "בני ברק|אברבנאל,105": [32.0962085, 34.8356018], "פתח תקווה|סעדיה גאון,8": [32.0880413, 34.8798192], "תל אביב - יפו|וילנסקי משה,24": [32.1279655, 34.8326792], "הרצליה|נורדאו,26": [32.173803, 34.8166718], "ראשון לציון|התזמורת,17": [31.969149, 34.7755824], "יקנעם עילית|הגיא,11": [32.6408748, 35.0819319], "פרדס חנה-כרכור|מצדה,314": [32.4653617, 34.9615105], "ראשון לציון|חיל הצנחנים,5": [31.9960115, 34.7407238], "כרמיאל|חטיבת יפתח,48": [32.903957, 35.2772717], "ראשון לציון|שינקין,18": [31.9721648, 34.8007835], "תל אביב - יפו|אבנר,1": [32.124794, 34.831915], "ראשון לציון|אבני החושן,2": [31.9816635, 34.7749667], "גבעת שמואל|הרימון,1": [32.0830084, 34.8505004], "רעננה|שברץ,24": [32.1829604, 34.8820683], "גני תקווה|דרך הים,3": [32.064056, 34.8780742], "בת ים|רייק חביבה,3": null, "זכרון יעקב|דרך אהרן,4": null, "אור עקיבא|גלפנשטיין מיכאל,1": [32.502102, 34.9177371], "בת ים|רמב\"ם,7": [32.0295246, 34.7460431], "חולון|גרינברג אורי צבי,6": [31.9977002, 34.7666642], "דימונה|שד בן גוריון": null, "ראשון לציון|נגבה,33": [31.9633075, 34.7764291], "מודיעין-מכבים-רעות|חטיבת הצנחנים,1": [31.9090836, 34.9974852], "בני ברק|אהרונוביץ ראובן,33": null, "חולון|פילדלפיה,6": [32.0275781, 34.7625626], "אשקלון|לכיש,9": [31.6673463, 34.5803084], "בת ים|בורוכוב,10": [32.0171294, 34.7415304], "רחובות|קאופמן חיים,1": [31.8843986, 34.8182009], "באר שבע|ייבין יהושע,7": [31.236563, 34.765277], "ראשון לציון|נחמיה,111": [31.9496431, 34.8261281], "סח'נין|אל ג'אבה": null, "ראשון לציון|החלמונית,19": [31.9747317, 34.784395], "אבן יהודה|העצמאות,140": [32.2699166, 34.884618], "כפר סבא|ביאליק,1": [32.1703856, 34.9079102], "נתניה|שד בן אב\"י,28": null, "נהריה|איריס,44": [32.9912867, 35.0896985], "תל אביב - יפו|יפה בצלאל,8": [32.065166, 34.775086], "חולון|הבקעה,3": null, "ירושלים|הגננת,29": [31.7305056, 35.1894652], "רעננה|הפלמ\"ח,2א": [32.1888981, 34.8771713], "תל אביב - יפו|שד' ששת הימים,6": null, "ירושלים|מן,7": [31.7607473, 35.1981136], "באר שבע|מודעי יצחק,67": [31.2672862, 34.809738], "נתניה|ברמן בני,4": [32.2821336, 34.8445242], "גן יבנה|צה\"ל,26": [31.7873054, 34.7056231], "קרית מוצקין|שד ויצמן,41": null, "צור הדסה|רכסים,11": [31.7137614, 35.1001642], "חיפה|ציון,7": [32.7907245, 35.0159769], "הרצליה|ההגנה,64": [32.1707267, 34.850649], "ירושלים|מעוז,1": [31.8178181, 35.202196], "הרצליה|יצחק שדה,20": [32.1651382, 34.861811], "רמת גן|הכבאים,25": [32.0625012, 34.8357286], "אשדוד|תשרי,11": [31.782087, 34.6403985], "ראשון לציון|שז\"ר זלמן,24": [31.9965046, 34.7402313], "רמת גן|הרא\"ה,212": [32.0671274, 34.8241126], "אשקלון|הצפצפה": [31.6723059, 34.5669234], "נתניה|גור מרדכי,4": [32.2729165, 34.8445856], "ראשון לציון|גרינשפן הרשל,6": null, "בני ברק|הרב הירש,27": [32.0803272, 34.8313725], "אלעד|אבן גבירול,1": [32.0538845, 34.9584204], "רמת גן|מנדס,55": [32.0550072, 34.8501118], "שדרות|משה רבנו,120": [31.5344927, 34.584951], "אשדוד|רשב\"י": [31.789185, 34.663259], "תל אביב - יפו|שבטי ישראל,53": [32.045603, 34.75505], "ירושלים|מירסקי יצחק,10": [31.8201276, 35.1934833], "פתח תקווה|אשכול לוי,2": [32.0782907, 34.8665363], "באר שבע|שריג נחום,37": [31.2867962, 34.8086741], "חולון|השומר,21": [32.0271056, 34.778526], "מודיעין-מכבים-רעות|נחליאלי,4": [31.8953696, 34.9926635], "קדימה-צורן|דרך לב השרון צורן,2": null, "גבעתיים|פועלי הרכבת,30": [32.0777065, 34.8179752], "אור יהודה|שד בגין מנחם,99": null, "רמת גן|אמנון ותמר,19": [32.0705078, 34.8269212], "אילת|שרה אימנו,10": null, "רמת השרון|אלון יגאל,4": [32.1295946, 34.8611792], "ירושלים|הדולב,423": [31.732852, 35.1881227], "תל אביב - יפו|דרזנר יחיאל,2": [32.127006, 34.805009], "ירושלים|בובליק גדליה,26": [31.8152653, 35.2013819], "אשדוד|שבט ראובן,2": null, "אשדוד|סירקין נחמן,2": [31.7714316, 34.6347512], "בני ברק|נורוק,31": [32.0995258, 34.8433802], "פתח תקווה|משה שמיר,2": [32.0986003, 34.8739241], "מזכרת בתיה|שד מוטה גור": null, "כפר סבא|רוזנבלום יאיר,29": [32.1883694, 34.8926321], "בני ברק|אחיה השילוני,2": [32.0889164, 34.8243929], "נתניה|יל\"ג,9": [32.3357745, 34.8616337], "באר שבע|הולצברג שמחה,6": [31.2455827, 34.7643163], "ירושלים|אידלזון אברהם,30": [31.8188895, 35.1906272], "אופקים|צאלון,1": [31.3020592, 34.619947], "נתניה|רייך לאון,4": [32.3406457, 34.857934], "קרית מוצקין|שד גושן משה,50": null, "גן יבנה|מירון": [31.7806828, 34.6958507], "נתניה|יהודה הלוי,35": [32.3204923, 34.8569837], "ראשון לציון|התזמורת,43": [31.9625638, 34.7716976], "תל מונד|הדקל,64": [32.2506028, 34.9184839], "באר שבע|שדרת הערים התאומות,43": null, "הרצליה|העצמאות,66": [32.1649316, 34.8431649], "חולון|חנקין,109": [32.0237482, 34.7790033], "גבעתיים|רביבים,1": [32.0650487, 34.8077269], "ראשון לציון|כצנלסון,26": [31.9681319, 34.7955786], "ראשון לציון|ריב\"ל,1": [31.9750341, 34.770891], "חולון|מוטה גור,6": [32.0099845, 34.782411], "פתח תקווה|הרב מימון,4": [32.0773543, 34.8923445], "רמת גן|אהרונסון שרה,32": [32.0611741, 34.8248628], "פתח תקווה|הבנים,5": [32.0753196, 34.8850119], "באר יעקב|בן יוסף שלמה,18": [31.9405884, 34.837528], "פתח תקווה|עידוד ישראל,5": [32.0715725, 34.8625533], "תל אביב - יפו|החשמונאים,92": [32.069163, 34.784353], "חדרה|האלון,30": [32.4217057, 34.9202859], "אשקלון|ניסן,1": [31.6734906, 34.5779932], "מודיעין-מכבים-רעות|נחל עיון,1": [31.8988226, 35.0119663], "ירושלים|הרב פרנק,20": [31.7642657, 35.1847181], "ביתר עילית|כנסת מרדכי,8": null, "באר שבע|דוד הראובני,31": [31.2632557, 34.7637939], "תל אביב - יפו|אנטוקולסקי,4": [32.08423, 34.782481], "ראשון לציון|קידוש השם,11": [31.9683089, 34.8121232], "גבעת זאב|מצפה,1": null, "ירושלים|הרב זווין,4": [31.8381325, 35.246992], "אור יהודה|ניצן,2": [32.0250244, 34.8735701], "אשדוד|הצוללים": [31.7969027, 34.6392846], "פתח תקווה|בראון אריה,3": [32.1040206, 34.8779173], "בני ברק|בעל התניא,12": [32.0786301, 34.8328875], "ראשון לציון|לוין מיכאל וחנה,14": null, "תל אביב - יפו|שטריקר,19": [32.0928344, 34.7878817], "הוד השרון|הדרים,12": [32.1613777, 34.8975454], "ירושלים|דולצ'ין,21": [31.7525367, 35.1667634], "נהריה|רמז,21": [33.0015727, 35.0904185], "נתניה|לנדאו שמואל,17": [32.3116093, 34.8847514], "הוד השרון|קורצ'אק יאנוש,1": null, "רמת גן|תל חי,3": [32.0545572, 34.8424646], "תל אביב - יפו|הרב הרצוג,11": [32.095396, 34.797093], "חיפה|ליבריה,11": [32.7691868, 35.003767]}